{
    "directed": true,
    "graph": {},
    "links": [
        {
            "Inverse Weight": 1.0,
            "key": 0,
            "source": "Bengals",
            "target": "Seahawks",
            "weight": 1
        },
        {
            "Inverse Weight": 0.041666666666666664,
            "key": 0,
            "source": "Bengals",
            "target": "49ers",
            "weight": 24
        },
        {
            "Inverse Weight": 0.25,
            "key": 0,
            "source": "Bengals",
            "target": "Bills",
            "weight": 4
        },
        {
            "Inverse Weight": 0.041666666666666664,
            "key": 0,
            "source": "Bengals",
            "target": "Steelers",
            "weight": 24
        },
        {
            "Inverse Weight": 0.3333333333333333,
            "key": 0,
            "source": "Bengals",
            "target": "Cardinals",
            "weight": 3
        },
        {
            "Inverse Weight": 0.16666666666666666,
            "key": 0,
            "source": "Bengals",
            "target": "Ravens",
            "weight": 6
        },
        {
            "Inverse Weight": 0.027777777777777776,
            "key": 1,
            "source": "Bengals",
            "target": "Ravens",
            "weight": 36
        },
        {
            "Inverse Weight": 0.1,
            "key": 0,
            "source": "Bengals",
            "target": "Jaguars",
            "weight": 10
        },
        {
            "Inverse Weight": 0.07142857142857142,
            "key": 0,
            "source": "Bengals",
            "target": "Rams",
            "weight": 14
        },
        {
            "Inverse Weight": 0.03333333333333333,
            "key": 0,
            "source": "Browns",
            "target": "Titans",
            "weight": 30
        },
        {
            "Inverse Weight": 0.14285714285714285,
            "key": 0,
            "source": "Browns",
            "target": "Rams",
            "weight": 7
        },
        {
            "Inverse Weight": 0.03571428571428571,
            "key": 0,
            "source": "Browns",
            "target": "49ers",
            "weight": 28
        },
        {
            "Inverse Weight": 0.25,
            "key": 0,
            "source": "Browns",
            "target": "Seahawks",
            "weight": 4
        },
        {
            "Inverse Weight": 0.07142857142857142,
            "key": 0,
            "source": "Browns",
            "target": "Patriots",
            "weight": 14
        },
        {
            "Inverse Weight": 0.2,
            "key": 0,
            "source": "Browns",
            "target": "Broncos",
            "weight": 5
        },
        {
            "Inverse Weight": 0.2,
            "key": 0,
            "source": "Ravens",
            "target": "Chiefs",
            "weight": 5
        },
        {
            "Inverse Weight": 0.06666666666666667,
            "key": 0,
            "source": "Ravens",
            "target": "Browns",
            "weight": 15
        },
        {
            "Inverse Weight": 0.03333333333333333,
            "key": 0,
            "source": "Steelers",
            "target": "Patriots",
            "weight": 30
        },
        {
            "Inverse Weight": 0.5,
            "key": 0,
            "source": "Steelers",
            "target": "Seahawks",
            "weight": 2
        },
        {
            "Inverse Weight": 0.25,
            "key": 0,
            "source": "Steelers",
            "target": "49ers",
            "weight": 4
        },
        {
            "Inverse Weight": 0.3333333333333333,
            "key": 0,
            "source": "Steelers",
            "target": "Ravens",
            "weight": 3
        },
        {
            "Inverse Weight": 0.16666666666666666,
            "key": 0,
            "source": "Bills",
            "target": "Patriots",
            "weight": 6
        },
        {
            "Inverse Weight": 0.05555555555555555,
            "key": 0,
            "source": "Bills",
            "target": "Eagles",
            "weight": 18
        },
        {
            "Inverse Weight": 0.3333333333333333,
            "key": 0,
            "source": "Bills",
            "target": "Browns",
            "weight": 3
        },
        {
            "Inverse Weight": 0.02040816326530612,
            "key": 0,
            "source": "Dolphins",
            "target": "Ravens",
            "weight": 49
        },
        {
            "Inverse Weight": 0.023255813953488372,
            "key": 0,
            "source": "Dolphins",
            "target": "Patriots",
            "weight": 43
        },
        {
            "Inverse Weight": 0.04,
            "key": 0,
            "source": "Dolphins",
            "target": "Cowboys",
            "weight": 25
        },
        {
            "Inverse Weight": 0.05,
            "key": 0,
            "source": "Dolphins",
            "target": "Chargers",
            "weight": 20
        },
        {
            "Inverse Weight": 1.0,
            "key": 0,
            "source": "Dolphins",
            "target": "Redskins",
            "weight": 1
        },
        {
            "Inverse Weight": 0.1,
            "key": 0,
            "source": "Dolphins",
            "target": "Bills",
            "weight": 10
        },
        {
            "Inverse Weight": 0.07692307692307693,
            "key": 0,
            "source": "Dolphins",
            "target": "Steelers",
            "weight": 13
        },
        {
            "Inverse Weight": 1.0,
            "key": 0,
            "source": "Jets",
            "target": "Bills",
            "weight": 1
        },
        {
            "Inverse Weight": 0.05,
            "key": 0,
            "source": "Jets",
            "target": "Browns",
            "weight": 20
        },
        {
            "Inverse Weight": 0.0625,
            "key": 0,
            "source": "Jets",
            "target": "Patriots",
            "weight": 16
        },
        {
            "Inverse Weight": 0.030303030303030304,
            "key": 1,
            "source": "Jets",
            "target": "Patriots",
            "weight": 33
        },
        {
            "Inverse Weight": 0.04,
            "key": 0,
            "source": "Jets",
            "target": "Eagles",
            "weight": 25
        },
        {
            "Inverse Weight": 0.07142857142857142,
            "key": 0,
            "source": "Jets",
            "target": "Jaguars",
            "weight": 14
        },
        {
            "Inverse Weight": 0.125,
            "key": 0,
            "source": "Jets",
            "target": "Dolphins",
            "weight": 8
        },
        {
            "Inverse Weight": 0.058823529411764705,
            "key": 0,
            "source": "Patriots",
            "target": "Ravens",
            "weight": 17
        },
        {
            "Inverse Weight": 0.16666666666666666,
            "key": 0,
            "source": "Colts",
            "target": "Chargers",
            "weight": 6
        },
        {
            "Inverse Weight": 0.14285714285714285,
            "key": 0,
            "source": "Colts",
            "target": "Raiders",
            "weight": 7
        },
        {
            "Inverse Weight": 0.5,
            "key": 0,
            "source": "Colts",
            "target": "Steelers",
            "weight": 2
        },
        {
            "Inverse Weight": 0.25,
            "key": 0,
            "source": "Colts",
            "target": "Dolphins",
            "weight": 4
        },
        {
            "Inverse Weight": 0.07142857142857142,
            "key": 0,
            "source": "Jaguars",
            "target": "Chiefs",
            "weight": 14
        },
        {
            "Inverse Weight": 1.0,
            "key": 0,
            "source": "Jaguars",
            "target": "Texans",
            "weight": 1
        },
        {
            "Inverse Weight": 0.043478260869565216,
            "key": 1,
            "source": "Jaguars",
            "target": "Texans",
            "weight": 23
        },
        {
            "Inverse Weight": 0.14285714285714285,
            "key": 0,
            "source": "Jaguars",
            "target": "Panthers",
            "weight": 7
        },
        {
            "Inverse Weight": 0.14285714285714285,
            "key": 0,
            "source": "Jaguars",
            "target": "Saints",
            "weight": 7
        },
        {
            "Inverse Weight": 0.5,
            "key": 0,
            "source": "Texans",
            "target": "Saints",
            "weight": 2
        },
        {
            "Inverse Weight": 0.16666666666666666,
            "key": 0,
            "source": "Texans",
            "target": "Panthers",
            "weight": 6
        },
        {
            "Inverse Weight": 0.14285714285714285,
            "key": 0,
            "source": "Texans",
            "target": "Colts",
            "weight": 7
        },
        {
            "Inverse Weight": 0.5,
            "key": 0,
            "source": "Titans",
            "target": "Colts",
            "weight": 2
        },
        {
            "Inverse Weight": 0.07692307692307693,
            "key": 0,
            "source": "Titans",
            "target": "Jaguars",
            "weight": 13
        },
        {
            "Inverse Weight": 0.14285714285714285,
            "key": 0,
            "source": "Titans",
            "target": "Bills",
            "weight": 7
        },
        {
            "Inverse Weight": 0.0625,
            "key": 0,
            "source": "Titans",
            "target": "Broncos",
            "weight": 16
        },
        {
            "Inverse Weight": 0.1,
            "key": 0,
            "source": "Titans",
            "target": "Panthers",
            "weight": 10
        },
        {
            "Inverse Weight": 0.125,
            "key": 0,
            "source": "Broncos",
            "target": "Raiders",
            "weight": 8
        },
        {
            "Inverse Weight": 0.5,
            "key": 0,
            "source": "Broncos",
            "target": "Bears",
            "weight": 2
        },
        {
            "Inverse Weight": 0.09090909090909091,
            "key": 0,
            "source": "Broncos",
            "target": "Packers",
            "weight": 11
        },
        {
            "Inverse Weight": 0.5,
            "key": 0,
            "source": "Broncos",
            "target": "Jaguars",
            "weight": 2
        },
        {
            "Inverse Weight": 0.041666666666666664,
            "key": 0,
            "source": "Broncos",
            "target": "Chiefs",
            "weight": 24
        },
        {
            "Inverse Weight": 0.5,
            "key": 0,
            "source": "Broncos",
            "target": "Colts",
            "weight": 2
        },
        {
            "Inverse Weight": 0.3333333333333333,
            "key": 0,
            "source": "Chargers",
            "target": "Lions",
            "weight": 3
        },
        {
            "Inverse Weight": 0.14285714285714285,
            "key": 0,
            "source": "Chargers",
            "target": "Texans",
            "weight": 7
        },
        {
            "Inverse Weight": 0.14285714285714285,
            "key": 0,
            "source": "Chargers",
            "target": "Broncos",
            "weight": 7
        },
        {
            "Inverse Weight": 0.14285714285714285,
            "key": 0,
            "source": "Chargers",
            "target": "Steelers",
            "weight": 7
        },
        {
            "Inverse Weight": 0.3333333333333333,
            "key": 0,
            "source": "Chargers",
            "target": "Titans",
            "weight": 3
        },
        {
            "Inverse Weight": 0.5,
            "key": 0,
            "source": "Chargers",
            "target": "Raiders",
            "weight": 2
        },
        {
            "Inverse Weight": 0.16666666666666666,
            "key": 0,
            "source": "Chiefs",
            "target": "Colts",
            "weight": 6
        },
        {
            "Inverse Weight": 0.14285714285714285,
            "key": 0,
            "source": "Chiefs",
            "target": "Texans",
            "weight": 7
        },
        {
            "Inverse Weight": 0.14285714285714285,
            "key": 0,
            "source": "Chiefs",
            "target": "Packers",
            "weight": 7
        },
        {
            "Inverse Weight": 0.3333333333333333,
            "key": 0,
            "source": "Chiefs",
            "target": "Titans",
            "weight": 3
        },
        {
            "Inverse Weight": 0.05555555555555555,
            "key": 0,
            "source": "Raiders",
            "target": "Chiefs",
            "weight": 18
        },
        {
            "Inverse Weight": 0.05,
            "key": 0,
            "source": "Raiders",
            "target": "Vikings",
            "weight": 20
        },
        {
            "Inverse Weight": 0.05555555555555555,
            "key": 0,
            "source": "Raiders",
            "target": "Packers",
            "weight": 18
        },
        {
            "Inverse Weight": 0.3333333333333333,
            "key": 0,
            "source": "Raiders",
            "target": "Texans",
            "weight": 3
        },
        {
            "Inverse Weight": 0.14285714285714285,
            "key": 0,
            "source": "Bears",
            "target": "Packers",
            "weight": 7
        },
        {
            "Inverse Weight": 0.3333333333333333,
            "key": 0,
            "source": "Bears",
            "target": "Raiders",
            "weight": 3
        },
        {
            "Inverse Weight": 0.09090909090909091,
            "key": 0,
            "source": "Bears",
            "target": "Saints",
            "weight": 11
        },
        {
            "Inverse Weight": 1.0,
            "key": 0,
            "source": "Bears",
            "target": "Chargers",
            "weight": 1
        },
        {
            "Inverse Weight": 0.125,
            "key": 0,
            "source": "Bears",
            "target": "Eagles",
            "weight": 8
        },
        {
            "Inverse Weight": 0.25,
            "key": 0,
            "source": "Lions",
            "target": "Chiefs",
            "weight": 4
        },
        {
            "Inverse Weight": 1.0,
            "key": 0,
            "source": "Lions",
            "target": "Packers",
            "weight": 1
        },
        {
            "Inverse Weight": 0.08333333333333333,
            "key": 0,
            "source": "Lions",
            "target": "Vikings",
            "weight": 12
        },
        {
            "Inverse Weight": 0.14285714285714285,
            "key": 0,
            "source": "Lions",
            "target": "Raiders",
            "weight": 7
        },
        {
            "Inverse Weight": 0.14285714285714285,
            "key": 0,
            "source": "Lions",
            "target": "Bears",
            "weight": 7
        },
        {
            "Inverse Weight": 0.14285714285714285,
            "key": 0,
            "source": "Packers",
            "target": "Eagles",
            "weight": 7
        },
        {
            "Inverse Weight": 0.06666666666666667,
            "key": 0,
            "source": "Packers",
            "target": "Chargers",
            "weight": 15
        },
        {
            "Inverse Weight": 0.2,
            "key": 0,
            "source": "Vikings",
            "target": "Packers",
            "weight": 5
        },
        {
            "Inverse Weight": 0.1,
            "key": 0,
            "source": "Vikings",
            "target": "Bears",
            "weight": 10
        },
        {
            "Inverse Weight": 0.3333333333333333,
            "key": 0,
            "source": "Vikings",
            "target": "Chiefs",
            "weight": 3
        },
        {
            "Inverse Weight": 0.5,
            "key": 0,
            "source": "Cowboys",
            "target": "Saints",
            "weight": 2
        },
        {
            "Inverse Weight": 0.1,
            "key": 0,
            "source": "Cowboys",
            "target": "Packers",
            "weight": 10
        },
        {
            "Inverse Weight": 0.5,
            "key": 0,
            "source": "Cowboys",
            "target": "Jets",
            "weight": 2
        },
        {
            "Inverse Weight": 0.25,
            "key": 0,
            "source": "Cowboys",
            "target": "Vikings",
            "weight": 4
        },
        {
            "Inverse Weight": 0.25,
            "key": 0,
            "source": "Eagles",
            "target": "Falcons",
            "weight": 4
        },
        {
            "Inverse Weight": 0.3333333333333333,
            "key": 0,
            "source": "Eagles",
            "target": "Lions",
            "weight": 3
        },
        {
            "Inverse Weight": 0.05555555555555555,
            "key": 0,
            "source": "Eagles",
            "target": "Vikings",
            "weight": 18
        },
        {
            "Inverse Weight": 0.037037037037037035,
            "key": 0,
            "source": "Eagles",
            "target": "Cowboys",
            "weight": 27
        },
        {
            "Inverse Weight": 0.05555555555555555,
            "key": 0,
            "source": "Giants",
            "target": "Cowboys",
            "weight": 18
        },
        {
            "Inverse Weight": 0.05263157894736842,
            "key": 1,
            "source": "Giants",
            "target": "Cowboys",
            "weight": 19
        },
        {
            "Inverse Weight": 0.07142857142857142,
            "key": 0,
            "source": "Giants",
            "target": "Bills",
            "weight": 14
        },
        {
            "Inverse Weight": 0.05555555555555555,
            "key": 0,
            "source": "Giants",
            "target": "Vikings",
            "weight": 18
        },
        {
            "Inverse Weight": 0.047619047619047616,
            "key": 0,
            "source": "Giants",
            "target": "Patriots",
            "weight": 21
        },
        {
            "Inverse Weight": 0.16666666666666666,
            "key": 0,
            "source": "Giants",
            "target": "Cardinals",
            "weight": 6
        },
        {
            "Inverse Weight": 0.2,
            "key": 0,
            "source": "Giants",
            "target": "Lions",
            "weight": 5
        },
        {
            "Inverse Weight": 0.14285714285714285,
            "key": 0,
            "source": "Giants",
            "target": "Jets",
            "weight": 7
        },
        {
            "Inverse Weight": 0.2,
            "key": 0,
            "source": "Redskins",
            "target": "Eagles",
            "weight": 5
        },
        {
            "Inverse Weight": 0.1,
            "key": 0,
            "source": "Redskins",
            "target": "Cowboys",
            "weight": 10
        },
        {
            "Inverse Weight": 0.0625,
            "key": 0,
            "source": "Redskins",
            "target": "Bears",
            "weight": 16
        },
        {
            "Inverse Weight": 0.047619047619047616,
            "key": 0,
            "source": "Redskins",
            "target": "Giants",
            "weight": 21
        },
        {
            "Inverse Weight": 0.038461538461538464,
            "key": 0,
            "source": "Redskins",
            "target": "Patriots",
            "weight": 26
        },
        {
            "Inverse Weight": 0.1111111111111111,
            "key": 0,
            "source": "Redskins",
            "target": "49ers",
            "weight": 9
        },
        {
            "Inverse Weight": 0.1,
            "key": 0,
            "source": "Redskins",
            "target": "Vikings",
            "weight": 10
        },
        {
            "Inverse Weight": 0.06666666666666667,
            "key": 0,
            "source": "Redskins",
            "target": "Bills",
            "weight": 15
        },
        {
            "Inverse Weight": 0.07142857142857142,
            "key": 0,
            "source": "Buccaneers",
            "target": "49ers",
            "weight": 14
        },
        {
            "Inverse Weight": 1.0,
            "key": 0,
            "source": "Buccaneers",
            "target": "Giants",
            "weight": 1
        },
        {
            "Inverse Weight": 0.14285714285714285,
            "key": 0,
            "source": "Buccaneers",
            "target": "Saints",
            "weight": 7
        },
        {
            "Inverse Weight": 0.09090909090909091,
            "key": 0,
            "source": "Buccaneers",
            "target": "Panthers",
            "weight": 11
        },
        {
            "Inverse Weight": 0.25,
            "key": 0,
            "source": "Buccaneers",
            "target": "Titans",
            "weight": 4
        },
        {
            "Inverse Weight": 0.16666666666666666,
            "key": 0,
            "source": "Buccaneers",
            "target": "Seahawks",
            "weight": 6
        },
        {
            "Inverse Weight": 0.0625,
            "key": 0,
            "source": "Falcons",
            "target": "Vikings",
            "weight": 16
        },
        {
            "Inverse Weight": 0.3333333333333333,
            "key": 0,
            "source": "Falcons",
            "target": "Colts",
            "weight": 3
        },
        {
            "Inverse Weight": 0.07142857142857142,
            "key": 0,
            "source": "Falcons",
            "target": "Titans",
            "weight": 14
        },
        {
            "Inverse Weight": 0.047619047619047616,
            "key": 0,
            "source": "Falcons",
            "target": "Texans",
            "weight": 21
        },
        {
            "Inverse Weight": 1.0,
            "key": 0,
            "source": "Falcons",
            "target": "Cardinals",
            "weight": 1
        },
        {
            "Inverse Weight": 0.037037037037037035,
            "key": 0,
            "source": "Falcons",
            "target": "Rams",
            "weight": 27
        },
        {
            "Inverse Weight": 0.14285714285714285,
            "key": 0,
            "source": "Falcons",
            "target": "Seahawks",
            "weight": 7
        },
        {
            "Inverse Weight": 0.3333333333333333,
            "key": 0,
            "source": "Panthers",
            "target": "Rams",
            "weight": 3
        },
        {
            "Inverse Weight": 0.16666666666666666,
            "key": 0,
            "source": "Panthers",
            "target": "Buccaneers",
            "weight": 6
        },
        {
            "Inverse Weight": 0.02631578947368421,
            "key": 0,
            "source": "Panthers",
            "target": "49ers",
            "weight": 38
        },
        {
            "Inverse Weight": 0.125,
            "key": 0,
            "source": "Panthers",
            "target": "Packers",
            "weight": 8
        },
        {
            "Inverse Weight": 0.05555555555555555,
            "key": 0,
            "source": "Saints",
            "target": "Rams",
            "weight": 18
        },
        {
            "Inverse Weight": 0.058823529411764705,
            "key": 0,
            "source": "Saints",
            "target": "Falcons",
            "weight": 17
        },
        {
            "Inverse Weight": 0.3333333333333333,
            "key": 0,
            "source": "49ers",
            "target": "Seahawks",
            "weight": 3
        },
        {
            "Inverse Weight": 0.16666666666666666,
            "key": 0,
            "source": "Cardinals",
            "target": "Ravens",
            "weight": 6
        },
        {
            "Inverse Weight": 0.05555555555555555,
            "key": 0,
            "source": "Cardinals",
            "target": "Panthers",
            "weight": 18
        },
        {
            "Inverse Weight": 0.058823529411764705,
            "key": 0,
            "source": "Cardinals",
            "target": "Seahawks",
            "weight": 17
        },
        {
            "Inverse Weight": 0.045454545454545456,
            "key": 0,
            "source": "Cardinals",
            "target": "Saints",
            "weight": 22
        },
        {
            "Inverse Weight": 0.3333333333333333,
            "key": 0,
            "source": "Cardinals",
            "target": "49ers",
            "weight": 3
        },
        {
            "Inverse Weight": 0.3333333333333333,
            "key": 0,
            "source": "Cardinals",
            "target": "Buccaneers",
            "weight": 3
        },
        {
            "Inverse Weight": 0.06666666666666667,
            "key": 0,
            "source": "Rams",
            "target": "Buccaneers",
            "weight": 15
        },
        {
            "Inverse Weight": 1.0,
            "key": 0,
            "source": "Rams",
            "target": "Seahawks",
            "weight": 1
        },
        {
            "Inverse Weight": 0.07692307692307693,
            "key": 0,
            "source": "Rams",
            "target": "49ers",
            "weight": 13
        },
        {
            "Inverse Weight": 0.2,
            "key": 0,
            "source": "Rams",
            "target": "Steelers",
            "weight": 5
        },
        {
            "Inverse Weight": 0.16666666666666666,
            "key": 0,
            "source": "Seahawks",
            "target": "Saints",
            "weight": 6
        },
        {
            "Inverse Weight": 0.07142857142857142,
            "key": 0,
            "source": "Seahawks",
            "target": "Ravens",
            "weight": 14
        }
    ],
    "multigraph": true,
    "nodes": [
        {
            "Conference": "AFC",
            "Division": "North",
            "Elo": 1325.486580188298,
            "Interceptions Thrown": 10,
            "Losses": 9,
            "Net Passing Yards": 2211,
            "Pagerank": 0.00468749999999998,
            "Pass Attempts": 367,
            "Pass Completions": 220,
            "Passing Touchdowns": 10,
            "Points Against": 28.77777777777778,
            "Points For": 15.222222222222221,
            "Primary": "#FB4F14",
            "Secondary": "#000000",
            "Tertiary": "#000000",
            "Ties": 0,
            "Total Yards": 316.1111111111111,
            "Touchdowns": 1.4444444444444444,
            "Wins": 0,
            "id": "Bengals"
        },
        {
            "Conference": "AFC",
            "Division": "North",
            "Elo": 1472.9253763033685,
            "Interceptions Thrown": 12,
            "Losses": 6,
            "Net Passing Yards": 2021,
            "Pagerank": 0.058822292286169094,
            "Pass Attempts": 313,
            "Pass Completions": 186,
            "Passing Touchdowns": 9,
            "Points Against": 24.555555555555557,
            "Points For": 19.0,
            "Primary": "#311D00",
            "Secondary": "#FF3C00",
            "Tertiary": "#000000",
            "Ties": 0,
            "Total Yards": 348.44444444444446,
            "Touchdowns": 2.0,
            "Wins": 3,
            "id": "Browns"
        },
        {
            "Conference": "AFC",
            "Division": "North",
            "Elo": 1607.4598074461203,
            "Interceptions Thrown": 6,
            "Losses": 2,
            "Net Passing Yards": 2020,
            "Pagerank": 0.08161731960495881,
            "Pass Attempts": 266,
            "Pass Completions": 177,
            "Passing Touchdowns": 16,
            "Points Against": 21.0,
            "Points For": 33.333333333333336,
            "Primary": "#241773",
            "Secondary": "#9E7C0C",
            "Tertiary": "#000000",
            "Ties": 0,
            "Total Yards": 421.6666666666667,
            "Touchdowns": 3.4444444444444446,
            "Wins": 7,
            "id": "Ravens"
        },
        {
            "Conference": "AFC",
            "Division": "North",
            "Elo": 1560.7027354274007,
            "Interceptions Thrown": 7,
            "Losses": 4,
            "Net Passing Yards": 1850,
            "Pagerank": 0.023953608003331444,
            "Pass Attempts": 299,
            "Pass Completions": 192,
            "Passing Touchdowns": 12,
            "Points Against": 20.11111111111111,
            "Points For": 21.444444444444443,
            "Primary": "#FFB612",
            "Secondary": "#101820",
            "Tertiary": "#000000",
            "Ties": 0,
            "Total Yards": 289.0,
            "Touchdowns": 1.8888888888888888,
            "Wins": 5,
            "id": "Steelers"
        },
        {
            "Conference": "AFC",
            "Division": "East",
            "Elo": 1496.6588245194148,
            "Interceptions Thrown": 8,
            "Losses": 3,
            "Net Passing Yards": 1913,
            "Pagerank": 0.011188518306674524,
            "Pass Attempts": 300,
            "Pass Completions": 179,
            "Passing Touchdowns": 10,
            "Points Against": 16.666666666666668,
            "Points For": 19.333333333333332,
            "Primary": "#00338D",
            "Secondary": "#C60C30",
            "Tertiary": "#000000",
            "Ties": 0,
            "Total Yards": 336.8888888888889,
            "Touchdowns": 2.2222222222222223,
            "Wins": 6,
            "id": "Bills"
        },
        {
            "Conference": "AFC",
            "Division": "East",
            "Elo": 1356.4929722054615,
            "Interceptions Thrown": 13,
            "Losses": 7,
            "Net Passing Yards": 1747,
            "Pagerank": 0.011299866490928153,
            "Pass Attempts": 317,
            "Pass Completions": 186,
            "Passing Touchdowns": 9,
            "Points Against": 29.77777777777778,
            "Points For": 13.222222222222221,
            "Primary": "#008E97",
            "Secondary": "#FC4C02",
            "Tertiary": "#005778",
            "Ties": 0,
            "Total Yards": 258.55555555555554,
            "Touchdowns": 1.4444444444444444,
            "Wins": 2,
            "id": "Dolphins"
        },
        {
            "Conference": "AFC",
            "Division": "East",
            "Elo": 1370.2506068289274,
            "Interceptions Thrown": 12,
            "Losses": 7,
            "Net Passing Yards": 1476,
            "Pagerank": 0.007206220244598466,
            "Pass Attempts": 283,
            "Pass Completions": 179,
            "Passing Touchdowns": 7,
            "Points Against": 26.444444444444443,
            "Points For": 14.444444444444445,
            "Primary": "#125740",
            "Secondary": "#000000",
            "Tertiary": "#000000",
            "Ties": 0,
            "Total Yards": 230.22222222222223,
            "Touchdowns": 1.2222222222222223,
            "Wins": 2,
            "id": "Jets"
        },
        {
            "Conference": "AFC",
            "Division": "East",
            "Elo": 1651.0557973957475,
            "Interceptions Thrown": 6,
            "Losses": 1,
            "Net Passing Yards": 2465,
            "Pagerank": 0.03745312595052019,
            "Pass Attempts": 359,
            "Pass Completions": 233,
            "Passing Touchdowns": 14,
            "Points Against": 10.88888888888889,
            "Points For": 30.0,
            "Primary": "#002244",
            "Secondary": "#C60C30",
            "Tertiary": "#B0B7BC",
            "Ties": 0,
            "Total Yards": 365.8888888888889,
            "Touchdowns": 3.111111111111111,
            "Wins": 8,
            "id": "Patriots"
        },
        {
            "Conference": "AFC",
            "Division": "South",
            "Elo": 1491.9399427843778,
            "Interceptions Thrown": 7,
            "Losses": 4,
            "Net Passing Yards": 1902,
            "Pagerank": 0.03461097801340163,
            "Pass Attempts": 302,
            "Pass Completions": 188,
            "Passing Touchdowns": 18,
            "Points Against": 21.444444444444443,
            "Points For": 21.555555555555557,
            "Primary": "#002C5F",
            "Secondary": "#A2AAAD",
            "Tertiary": "#000000",
            "Ties": 0,
            "Total Yards": 339.3333333333333,
            "Touchdowns": 2.4444444444444446,
            "Wins": 5,
            "id": "Colts"
        },
        {
            "Conference": "AFC",
            "Division": "South",
            "Elo": 1467.2995220161472,
            "Interceptions Thrown": 5,
            "Losses": 5,
            "Net Passing Yards": 2228,
            "Pagerank": 0.015144882444731628,
            "Pass Attempts": 316,
            "Pass Completions": 193,
            "Passing Touchdowns": 14,
            "Points Against": 21.0,
            "Points For": 19.555555555555557,
            "Primary": "#D7A22A",
            "Secondary": "#006778",
            "Tertiary": "#101820",
            "Ties": 0,
            "Total Yards": 377.22222222222223,
            "Touchdowns": 1.6666666666666667,
            "Wins": 4,
            "id": "Jaguars"
        },
        {
            "Conference": "AFC",
            "Division": "South",
            "Elo": 1574.8157154793487,
            "Interceptions Thrown": 6,
            "Losses": 3,
            "Net Passing Yards": 2285,
            "Pagerank": 0.03985439704100621,
            "Pass Attempts": 303,
            "Pass Completions": 212,
            "Passing Touchdowns": 18,
            "Points Against": 21.22222222222222,
            "Points For": 26.444444444444443,
            "Primary": "#03202F",
            "Secondary": "#A71930",
            "Tertiary": "#000000",
            "Ties": 0,
            "Total Yards": 396.6666666666667,
            "Touchdowns": 3.111111111111111,
            "Wins": 6,
            "id": "Texans"
        },
        {
            "Conference": "AFC",
            "Division": "South",
            "Elo": 1497.4158377398262,
            "Interceptions Thrown": 6,
            "Losses": 5,
            "Net Passing Yards": 2062,
            "Pagerank": 0.0365873553213016,
            "Pass Attempts": 296,
            "Pass Completions": 192,
            "Passing Touchdowns": 15,
            "Points Against": 19.7,
            "Points For": 20.3,
            "Primary": "#0C2340",
            "Secondary": "#418FDE",
            "Tertiary": "#C8102E",
            "Ties": 0,
            "Total Yards": 319.3,
            "Touchdowns": 2.4,
            "Wins": 5,
            "id": "Titans"
        },
        {
            "Conference": "AFC",
            "Division": "West",
            "Elo": 1467.6722010521066,
            "Interceptions Thrown": 5,
            "Losses": 6,
            "Net Passing Yards": 1797,
            "Pagerank": 0.028106973320808915,
            "Pass Attempts": 282,
            "Pass Completions": 183,
            "Passing Touchdowns": 8,
            "Points Against": 18.88888888888889,
            "Points For": 16.555555555555557,
            "Primary": "#FB4F14",
            "Secondary": "#002244",
            "Tertiary": "#000000",
            "Ties": 0,
            "Total Yards": 311.55555555555554,
            "Touchdowns": 1.6666666666666667,
            "Wins": 3,
            "id": "Broncos"
        },
        {
            "Conference": "AFC",
            "Division": "West",
            "Elo": 1499.5280721516224,
            "Interceptions Thrown": 10,
            "Losses": 6,
            "Net Passing Yards": 2701,
            "Pagerank": 0.04977378024467434,
            "Pass Attempts": 365,
            "Pass Completions": 241,
            "Passing Touchdowns": 14,
            "Points Against": 19.4,
            "Points For": 20.7,
            "Primary": "#FFC20E",
            "Secondary": "#002A5E",
            "Tertiary": "#0080C6",
            "Ties": 0,
            "Total Yards": 356.2,
            "Touchdowns": 2.1,
            "Wins": 4,
            "id": "Chargers"
        },
        {
            "Conference": "AFC",
            "Division": "West",
            "Elo": 1570.3085536033661,
            "Interceptions Thrown": 1,
            "Losses": 4,
            "Net Passing Yards": 3136,
            "Pagerank": 0.05028348215412196,
            "Pass Attempts": 383,
            "Pass Completions": 252,
            "Passing Touchdowns": 22,
            "Points Against": 23.9,
            "Points For": 28.4,
            "Primary": "#E31837",
            "Secondary": "#FFB81C",
            "Tertiary": "#000000",
            "Ties": 0,
            "Total Yards": 404.4,
            "Touchdowns": 2.9,
            "Wins": 6,
            "id": "Chiefs"
        },
        {
            "Conference": "AFC",
            "Division": "West",
            "Elo": 1485.2556517981868,
            "Interceptions Thrown": 4,
            "Losses": 4,
            "Net Passing Yards": 2162,
            "Pagerank": 0.026572018987952813,
            "Pass Attempts": 284,
            "Pass Completions": 201,
            "Passing Touchdowns": 15,
            "Points Against": 26.666666666666668,
            "Points For": 23.11111111111111,
            "Primary": "#A5ACAF",
            "Secondary": "#000000",
            "Tertiary": "#000000",
            "Ties": 0,
            "Total Yards": 370.1111111111111,
            "Touchdowns": 2.6666666666666665,
            "Wins": 5,
            "id": "Raiders"
        },
        {
            "Conference": "NFC",
            "Division": "North",
            "Elo": 1512.980608801491,
            "Interceptions Thrown": 5,
            "Losses": 5,
            "Net Passing Yards": 1648,
            "Pagerank": 0.024982358475822943,
            "Pass Attempts": 299,
            "Pass Completions": 196,
            "Passing Touchdowns": 11,
            "Points Against": 17.444444444444443,
            "Points For": 18.0,
            "Primary": "#0B162A",
            "Secondary": "#C83803",
            "Tertiary": "#000000",
            "Ties": 0,
            "Total Yards": 262.22222222222223,
            "Touchdowns": 1.7777777777777777,
            "Wins": 4,
            "id": "Bears"
        },
        {
            "Conference": "NFC",
            "Division": "North",
            "Elo": 1438.053230816218,
            "Interceptions Thrown": 6,
            "Losses": 5,
            "Net Passing Yards": 2621,
            "Pagerank": 0.010961936678090861,
            "Pass Attempts": 337,
            "Pass Completions": 214,
            "Passing Touchdowns": 20,
            "Points Against": 26.333333333333332,
            "Points For": 24.11111111111111,
            "Primary": "#0076B6",
            "Secondary": "#B0B7BC",
            "Tertiary": "#000000",
            "Ties": 1,
            "Total Yards": 387.55555555555554,
            "Touchdowns": 2.4444444444444446,
            "Wins": 3,
            "id": "Lions"
        },
        {
            "Conference": "NFC",
            "Division": "North",
            "Elo": 1621.7249596978759,
            "Interceptions Thrown": 2,
            "Losses": 2,
            "Net Passing Yards": 2539,
            "Pagerank": 0.05848545223344458,
            "Pass Attempts": 347,
            "Pass Completions": 225,
            "Passing Touchdowns": 17,
            "Points Against": 20.5,
            "Points For": 25.0,
            "Primary": "#203731",
            "Secondary": "#FFB612",
            "Tertiary": "#000000",
            "Ties": 0,
            "Total Yards": 355.0,
            "Touchdowns": 3.0,
            "Wins": 8,
            "id": "Packers"
        },
        {
            "Conference": "NFC",
            "Division": "North",
            "Elo": 1585.8799830614053,
            "Interceptions Thrown": 3,
            "Losses": 3,
            "Net Passing Yards": 2313,
            "Pagerank": 0.03523615070648192,
            "Pass Attempts": 285,
            "Pass Completions": 197,
            "Passing Touchdowns": 18,
            "Points Against": 18.2,
            "Points For": 26.2,
            "Primary": "#4F2683",
            "Secondary": "#FFC62F",
            "Tertiary": "#000000",
            "Ties": 0,
            "Total Yards": 384.3,
            "Touchdowns": 3.1,
            "Wins": 7,
            "id": "Vikings"
        },
        {
            "Conference": "NFC",
            "Division": "East",
            "Elo": 1517.0264268476944,
            "Interceptions Thrown": 9,
            "Losses": 4,
            "Net Passing Yards": 2692,
            "Pagerank": 0.02325021744204357,
            "Pass Attempts": 319,
            "Pass Completions": 218,
            "Passing Touchdowns": 18,
            "Points Against": 18.88888888888889,
            "Points For": 27.88888888888889,
            "Primary": "#041E42",
            "Secondary": "#869397",
            "Tertiary": "#000000",
            "Ties": 0,
            "Total Yards": 437.3333333333333,
            "Touchdowns": 3.2222222222222223,
            "Wins": 5,
            "id": "Cowboys"
        },
        {
            "Conference": "NFC",
            "Division": "East",
            "Elo": 1546.230023732142,
            "Interceptions Thrown": 5,
            "Losses": 4,
            "Net Passing Yards": 1977,
            "Pagerank": 0.03399694442727067,
            "Pass Attempts": 309,
            "Pass Completions": 193,
            "Passing Touchdowns": 15,
            "Points Against": 23.666666666666668,
            "Points For": 24.88888888888889,
            "Primary": "#004C54",
            "Secondary": "#A5ACAF",
            "Tertiary": "#000000",
            "Ties": 0,
            "Total Yards": 341.0,
            "Touchdowns": 2.7777777777777777,
            "Wins": 5,
            "id": "Eagles"
        },
        {
            "Conference": "NFC",
            "Division": "East",
            "Elo": 1360.6449907000663,
            "Interceptions Thrown": 10,
            "Losses": 8,
            "Net Passing Yards": 2280,
            "Pagerank": 0.0058604316819815825,
            "Pass Attempts": 386,
            "Pass Completions": 243,
            "Passing Touchdowns": 17,
            "Points Against": 28.9,
            "Points For": 20.3,
            "Primary": "#0B2265",
            "Secondary": "#A71930",
            "Tertiary": "#A5ACAF",
            "Ties": 0,
            "Total Yards": 322.2,
            "Touchdowns": 2.3,
            "Wins": 2,
            "id": "Giants"
        },
        {
            "Conference": "NFC",
            "Division": "East",
            "Elo": 1351.4797097566077,
            "Interceptions Thrown": 9,
            "Losses": 8,
            "Net Passing Yards": 1524,
            "Pagerank": 0.004747157680231607,
            "Pass Attempts": 260,
            "Pass Completions": 171,
            "Passing Touchdowns": 9,
            "Points Against": 24.333333333333332,
            "Points For": 12.0,
            "Primary": "#773141",
            "Secondary": "#FFB612",
            "Tertiary": "#000000",
            "Ties": 0,
            "Total Yards": 258.77777777777777,
            "Touchdowns": 1.2222222222222223,
            "Wins": 1,
            "id": "Redskins"
        },
        {
            "Conference": "NFC",
            "Division": "South",
            "Elo": 1440.6196017372151,
            "Interceptions Thrown": 14,
            "Losses": 6,
            "Net Passing Yards": 2558,
            "Pagerank": 0.02106258511514218,
            "Pass Attempts": 355,
            "Pass Completions": 212,
            "Passing Touchdowns": 17,
            "Points Against": 31.0,
            "Points For": 28.88888888888889,
            "Primary": "#D50A0A",
            "Secondary": "#0A0A08",
            "Tertiary": "#FF7900",
            "Ties": 0,
            "Total Yards": 385.55555555555554,
            "Touchdowns": 3.0,
            "Wins": 3,
            "id": "Buccaneers"
        },
        {
            "Conference": "NFC",
            "Division": "South",
            "Elo": 1414.2180645975398,
            "Interceptions Thrown": 10,
            "Losses": 7,
            "Net Passing Yards": 2710,
            "Pagerank": 0.024215312683133806,
            "Pass Attempts": 378,
            "Pass Completions": 267,
            "Passing Touchdowns": 19,
            "Points Against": 28.77777777777778,
            "Points For": 21.22222222222222,
            "Primary": "#A71930",
            "Secondary": "#000000",
            "Tertiary": "#A5ACAF",
            "Ties": 0,
            "Total Yards": 377.8888888888889,
            "Touchdowns": 2.4444444444444446,
            "Wins": 2,
            "id": "Falcons"
        },
        {
            "Conference": "NFC",
            "Division": "South",
            "Elo": 1529.2424920580502,
            "Interceptions Thrown": 6,
            "Losses": 4,
            "Net Passing Yards": 1927,
            "Pagerank": 0.03220359119632571,
            "Pass Attempts": 323,
            "Pass Completions": 193,
            "Passing Touchdowns": 10,
            "Points Against": 25.333333333333332,
            "Points For": 25.0,
            "Primary": "#0085CA",
            "Secondary": "#101820",
            "Tertiary": "#BFC0BF",
            "Ties": 0,
            "Total Yards": 345.55555555555554,
            "Touchdowns": 2.6666666666666665,
            "Wins": 5,
            "id": "Panthers"
        },
        {
            "Conference": "NFC",
            "Division": "South",
            "Elo": 1635.3436819921453,
            "Interceptions Thrown": 5,
            "Losses": 2,
            "Net Passing Yards": 2346,
            "Pagerank": 0.04191506880018409,
            "Pass Attempts": 334,
            "Pass Completions": 236,
            "Passing Touchdowns": 14,
            "Points Against": 20.22222222222222,
            "Points For": 22.666666666666668,
            "Primary": "#D3BC8D",
            "Secondary": "#101820",
            "Tertiary": "#000000",
            "Ties": 0,
            "Total Yards": 379.1111111111111,
            "Touchdowns": 2.111111111111111,
            "Wins": 7,
            "id": "Saints"
        },
        {
            "Conference": "NFC",
            "Division": "West",
            "Elo": 1590.9417720838708,
            "Interceptions Thrown": 8,
            "Losses": 1,
            "Net Passing Yards": 1969,
            "Pagerank": 0.06016364428622798,
            "Pass Attempts": 273,
            "Pass Completions": 185,
            "Passing Touchdowns": 14,
            "Points Against": 14.333333333333334,
            "Points For": 28.77777777777778,
            "Primary": "#AA0000",
            "Secondary": "#B3995D",
            "Tertiary": "#000000",
            "Ties": 0,
            "Total Yards": 373.8888888888889,
            "Touchdowns": 2.888888888888889,
            "Wins": 8,
            "id": "49ers"
        },
        {
            "Conference": "NFC",
            "Division": "West",
            "Elo": 1390.183373962091,
            "Interceptions Thrown": 5,
            "Losses": 6,
            "Net Passing Yards": 2357,
            "Pagerank": 0.005293488881863093,
            "Pass Attempts": 362,
            "Pass Completions": 231,
            "Passing Touchdowns": 12,
            "Points Against": 28.1,
            "Points For": 22.2,
            "Primary": "#97233F",
            "Secondary": "#000000",
            "Tertiary": "#FFB612",
            "Ties": 1,
            "Total Yards": 351.7,
            "Touchdowns": 2.1,
            "Wins": 3,
            "id": "Cardinals"
        },
        {
            "Conference": "NFC",
            "Division": "West",
            "Elo": 1548.540162989282,
            "Interceptions Thrown": 10,
            "Losses": 4,
            "Net Passing Yards": 2532,
            "Pagerank": 0.03518214665211857,
            "Pass Attempts": 357,
            "Pass Completions": 215,
            "Passing Touchdowns": 11,
            "Points Against": 21.22222222222222,
            "Points For": 25.11111111111111,
            "Primary": "#002244",
            "Secondary": "#866D4B",
            "Tertiary": "#000000",
            "Ties": 0,
            "Total Yards": 377.55555555555554,
            "Touchdowns": 2.4444444444444446,
            "Wins": 5,
            "id": "Rams"
        },
        {
            "Conference": "NFC",
            "Division": "West",
            "Elo": 1621.6207202265855,
            "Interceptions Thrown": 2,
            "Losses": 2,
            "Net Passing Yards": 2560,
            "Pagerank": 0.0652811946444571,
            "Pass Attempts": 327,
            "Pass Completions": 224,
            "Passing Touchdowns": 23,
            "Points Against": 25.4,
            "Points For": 27.5,
            "Primary": "#002244",
            "Secondary": "#69BE28",
            "Tertiary": "#A5ACAF",
            "Ties": 0,
            "Total Yards": 389.4,
            "Touchdowns": 3.0,
            "Wins": 8,
            "id": "Seahawks"
        }
    ]
}